xamppfixer/__init__.py
xamppfixer/fixer.py
xamppfixer-1.0.2.dist-info/METADATA
xamppfixer-1.0.2.dist-info/WHEEL
xamppfixer-1.0.2.dist-info/entry_points.txt
xamppfixer-1.0.2.dist-info/top_level.txt
xamppfixer-1.0.2.dist-info/RECORD
